niceshell/__init__.py
niceshell/core.py
niceshell/core.pyi
niceshell/extra.py
niceshell/extra.pyi
niceshell/gnu_coreutils.py
niceshell/gnu_coreutils.pyi
niceshell/tests/test_core.py
niceshell/tests/test_extra.py
niceshell/tests/test_gnu_coreutils.py
niceshell-2.0.3.dist-info/LICENSE
niceshell-2.0.3.dist-info/METADATA
niceshell-2.0.3.dist-info/WHEEL
niceshell-2.0.3.dist-info/top_level.txt
niceshell-2.0.3.dist-info/RECORD
