Metadata-Version: 2.1
Name: niceshell
Version: 2.0.3
Summary: Integration of shell and basic GNU core unilities for better coding.
Home-page: https://github.com/Andrew15-5/niceshell
Download-URL: https://github.com/Andrew15-5/niceshell/releases/download/v2.0.3/niceshell-2.0.3-py3-none-any.whl
Author: Andrew Voynov
Author-email: andrewvoynov.b@gmail.com
License: MIT
Keywords: nice,shell,GNU,coreutils,sh
Platform: UNKNOWN
Classifier: Development Status :: 5 - Production/Stable
Classifier: Intended Audience :: Developers
Classifier: License :: OSI Approved :: MIT License
Classifier: Operating System :: Unix
Classifier: Programming Language :: Python :: 3
Classifier: Topic :: System :: System Shells
Requires-Python: >=3.6
License-File: LICENSE
Requires-Dist: regex
Provides-Extra: pytest
Requires-Dist: pytest ; extra == 'pytest'
